ag_ui_langgraph/__init__.py
ag_ui_langgraph/agent.py
ag_ui_langgraph/endpoint.py
ag_ui_langgraph/types.py
ag_ui_langgraph/utils.py
ag_ui_langgraph-0.0.23.dist-info/METADATA
ag_ui_langgraph-0.0.23.dist-info/WHEEL
ag_ui_langgraph-0.0.23.dist-info/entry_points.txt
ag_ui_langgraph-0.0.23.dist-info/RECORD
