Metadata-Version: 2.3
Name: ag-ui-langgraph
Version: 0.0.23
Summary: Implementation of the AG-UI protocol for LangGraph.
Author: Ran Shem Tov
Author-email: ran@copilotkit.ai
Requires-Python: >=3.10,<3.14
Classifier: Programming Language :: Python :: 3
Classifier: Programming Language :: Python :: 3.10
Classifier: Programming Language :: Python :: 3.11
Classifier: Programming Language :: Python :: 3.12
Classifier: Programming Language :: Python :: 3.13
Provides-Extra: fastapi
Requires-Dist: ag-ui-protocol (>=0.1.10,<0.2.0)
Requires-Dist: fastapi (>=0.115.12,<0.116.0) ; extra == "fastapi"
Requires-Dist: langchain (>=0.3.0)
Requires-Dist: langchain-core (>=0.3.0)
Requires-Dist: langgraph (>=0.3.25,<1.1.0)
Requires-Dist: pydantic (>=2.0.0)
